pytorch_wpe.py
pytorch_wpe-0.0.1.dist-info/LICENCE
pytorch_wpe-0.0.1.dist-info/METADATA
pytorch_wpe-0.0.1.dist-info/WHEEL
pytorch_wpe-0.0.1.dist-info/top_level.txt
pytorch_wpe-0.0.1.dist-info/RECORD
