Metadata-Version: 1.0
Name: pytorch-wpe
Version: 0.0.1
Summary: A pytorch implementation of Weighted Prediction Error
Home-page: UNKNOWN
Author: UNKNOWN
Author-email: UNKNOWN
License: UNKNOWN
Platform: UNKNOWN
